senator_fec_data/__init__.py
senator_fec_data/data/senators_cfm.xml
senator_fec_data/senator_fec_data.py
senator_fec_data-0.1.0.dist-info/LICENSE
senator_fec_data-0.1.0.dist-info/WHEEL
senator_fec_data-0.1.0.dist-info/METADATA
senator_fec_data-0.1.0.dist-info/RECORD
